YAMScrobbler-0.69.data/scripts/yams
YAMScrobbler-0.69.dist-info/LICENSE.txt
YAMScrobbler-0.69.dist-info/METADATA
YAMScrobbler-0.69.dist-info/RECORD
YAMScrobbler-0.69.dist-info/WHEEL
YAMScrobbler-0.69.dist-info/top_level.txt
yams/__init__.py
yams/__main__.py
yams/configure.py
yams/scrobble.py
