Metadata-Version: 2.1
Name: YAMScrobbler
Version: 0.69
Summary: Yet Another MPD Scrobbler (for Last.FM!)
Home-page: https://github.com/berulacks/yams
Author: Derin Yarsuvat
Author-email: derin@ml1.net
License: GPLv3
Download-URL: https://github.com/Berulacks/yams/releases/download/0.69/yams-0.69-py3-none-any.whl
Platform: UNKNOWN
Requires-Python: >=3
Requires-Dist: python-mpd2 (==1.0.0)
Requires-Dist: PyYAML (==4.2b4)
Requires-Dist: requests (==2.21.0)
